{
  "projects": [
    {
      "id": "proactive-employee",
      "title": "Proactive Employee System: Strategic Value Creation",
      "status": "in-progress",
      "priority": 1,
      "summary": "Develop autonomous capability to create strategic value through self-improvement and independent problem-solving",
      "details": "**Strategic Focus:**\n- Transform from task completion to value creation\n- Develop independent learning and innovation capabilities\n- Create substantive improvements to existing systems\n- Demonstrate strategic thinking and autonomous decision-making",
      "lastUpdated": "2026-01-30",
      "keyUpdates": [
        "Rewrote master prompt to emphasize strategic WHY",
        "Expanded philosophical framework for autonomous work",
        "Clarified decision-making principles"
      ]
    }
  ]
}